boruta/__init__.py
boruta/boruta_py.py
boruta/examples/test_X.csv
boruta/examples/test_y.csv
Boruta-0.4.3.dist-info/LICENSE
Boruta-0.4.3.dist-info/METADATA
Boruta-0.4.3.dist-info/WHEEL
Boruta-0.4.3.dist-info/top_level.txt
Boruta-0.4.3.dist-info/RECORD
