Metadata-Version: 2.1
Name: Boruta
Version: 0.4.3
Summary: Python Implementation of Boruta Feature Selection
Home-page: https://github.com/danielhomola/boruta_py
Download-URL: https://github.com/danielhomola/boruta_py/tarball/0.1.5
Author: Daniel Homola
Author-email: dani.homola@gmail.com
License: BSD 3 clause
Keywords: feature selection,machine learning,random forest
License-File: LICENSE
